neatjson/__init__.py
neatjson/py.typed
neatjson-0.10.8.dist-info/METADATA
neatjson-0.10.8.dist-info/WHEEL
neatjson-0.10.8.dist-info/top_level.txt
neatjson-0.10.8.dist-info/RECORD
