Metadata-Version: 2.4
Name: neatjson
Version: 0.10.8
Summary: Pretty-print your JSON with more power than json.dumps provides.
Author-email: Gavin Kistner <gavin@phrogz.net>
Maintainer-email: Gavin Kistner <gavin@phrogz.net>
License: MIT
Project-URL: Homepage, https://github.com/Phrogz/NeatJSON
Project-URL: Documentation, https://github.com/Phrogz/NeatJSON#readme
Project-URL: Repository, https://github.com/Phrogz/NeatJSON
Project-URL: Issues, https://github.com/Phrogz/NeatJSON/issues
Keywords: json,pretty-print,formatting,serialization
Classifier: Development Status :: 5 - Production/Stable
Classifier: Intended Audience :: Developers
Classifier: License :: OSI Approved :: MIT License
Classifier: Operating System :: OS Independent
Classifier: Programming Language :: Python :: 3
Classifier: Programming Language :: Python :: 3.11
Classifier: Programming Language :: Python :: 3.12
Classifier: Programming Language :: Python :: 3.13
Classifier: Topic :: Software Development :: Libraries :: Python Modules
Classifier: Topic :: Text Processing :: General
Classifier: Typing :: Typed
Requires-Python: >=3.11
Provides-Extra: dev
Requires-Dist: pytest>=7.0; extra == "dev"
Requires-Dist: mypy>=1.0; extra == "dev"
